{
  "status": "building",
  "user_goal": "BL-SEC-POLISH — 安全杂项合并（AUTH 硬化 + SSRF/CT + 脚本硬化）",
  "total_features": 4,
  "completed_features": 0,
  "fix_rounds": 0,
  "current_sprint": "BL-SEC-POLISH",
  "last_updated": "2026-04-19T17:00:00Z",
  "reference_docs": [
    "docs/specs/BL-SEC-POLISH-spec.md",
    "docs/code-review/backend-fullscan-2026-04-17.md",
    "docs/code-review/batch-06-security.md",
    "docs/code-review/batch-08-hooks-scripts.md"
  ],
  "role_assignments": null,
  "docs": {
    "spec": "docs/specs/BL-SEC-POLISH-spec.md",
    "test_cases": null,
    "signoff": null,
    "framework_reviewed": false
  },
  "evaluator_feedback": null,
  "generator_handoff": null,
  "session_notes": {
    "Kimi": "Planner 一次完成：\n\n(1) BL-INFRA-RESILIENCE done 收尾（15/15 PASS，fix_rounds=1 仅修 stream cancel）。关键产物：fetchWithTimeout 双 API + rpmCheck Lua（生产探针 cmdstat_eval +9 实测）+ reconcile batch（40→5 次 DB 往返）。\n\n(2) 初始化 BL-SEC-POLISH（Path A 第 9 批，P2-polish 首批，1.5d 合并批次，4 features：3 generator + 1 codex）。合并原 BL-SEC-AUTH-HYGIENE + BL-SEC-SSRF-INPUT + BL-SCRIPT-HYGIENE 三批，覆盖 H-7/9/10 + H-27/28 + H-42-46 共 10 个加固点。\n\nspec 遵守新铁律，所有 file:line 已核实：\n- `login/route.ts:28` bcrypt.compare 在 :33 deletedAt + :36 suspended 检查之前（时序 oracle 属实）\n- `login/route.ts:43` bcrypt.hash cost=10（应 12）\n- `test-webhook/route.ts:37` 无 SSRF 过滤\n- `images/proxy/:48-52` Content-Type 透传\n- `stress-test.ts:230,352-353` 硬编码 '2026-04-04'\n- `setup-zero-balance-test.ts:38` passwordHash='dummy' 非 bcrypt 格式\n- `run-template.ts:86-119` test_mode 分支 return 在 :122 checkRateLimit 之前（确实跳过限流）\n\n关键设计决策：\n- F-SP-01 suspended 账号也返 401 + 内部日志（防账号枚举），dummy bcrypt 或 100ms 固定延迟抗时序\n- F-SP-02 isSafeWebhookUrl 仅 https + DNS 解析检查 RFC1918 + 元数据 + loopback + ULA；image-proxy 白名单正则\n- F-SP-03 test_mode rate limit 提前到分支前，保留 '不扣费' 特性（runTemplateTest 内部不变）\n\nPath A 进度 9/11。剩余 2 批（INFRA-ARCHIVE 1d + FE-DS-SHADCN 2d）。\n\n未消化 framework 提案 1 条（Next.js 私有目录）继续留 Path A 全部完成后批量同步。",
    "Reviewer": null
  }
}
