{
  "status": "building",
  "user_goal": "P4-1b-output-routing: 输出层简化 + 路由验证 + 废弃旧 fallback 代码",
  "total_features": 5,
  "completed_features": 0,
  "fix_rounds": 0,
  "current_sprint": null,
  "last_updated": "2026-04-08T16:00:00Z",
  "reference_docs": [
    "docs/specs/P4-model-aggregation-PRD.md",
    "docs/specs/P4-model-aggregation-spec.md"
  ],
  "role_assignments": {
    "planner": "Kimi",
    "generator": "Johnsong",
    "evaluator": "Reviewer"
  },
  "docs": {
    "spec": "docs/specs/P4-model-aggregation-spec.md",
    "test_cases": null,
    "signoff": null,
    "framework_reviewed": false
  },
  "evaluator_feedback": null,
  "generator_handoff": null
}
