{
  "status": "building",
  "user_goal": "UI-UNIFY — 抽取 9 个缺失的公共组件 + 改造 12 个 console 页面 + 统一 heading scale + 合并 BL-121/122/123 bug 修复",
  "total_features": 13,
  "completed_features": 6,
  "fix_rounds": 0,
  "current_sprint": "F-UU-07",
  "last_updated": "2026-04-13T10:50:00Z",
  "reference_docs": [
    "docs/specs/UI-UNIFY-spec.md"
  ],
  "role_assignments": null,
  "docs": {
    "spec": "docs/specs/UI-UNIFY-spec.md",
    "test_cases": null,
    "signoff": null,
    "framework_reviewed": false
  },
  "evaluator_feedback": null,
  "generator_handoff": null,
  "session_notes": {
    "Kimi": "Planner 启动 UI-UNIFY 批次（12 generator + 1 codex = 13 条）。来源：生产 UI 一致性审查，根因是重构到新设计系统时没有抽取公共组件。第一阶段 F-UU-01~06 建立组件基础设施（PageContainer/PageHeader/TableCard/KPICard/StatusChip/CTABanner/SectionCard/TableLoader/PageLoader/EmptyState/Button gradient variant）；第二阶段 F-UU-07~12 改造页面并修复 BL-121/122/123；第三阶段 F-UU-13 全量验收。所有页面改造必须按 test-lifecycle.md 规则同 commit 补 regression test。DX-POLISH 生产待执行 fix-dp-06-model-data.ts --apply。",
    "Reviewer": null
  }
}
